{
  "project_info": {
    "project_number": "504335149376",
    "project_id": "dahl-4d255",
    "storage_bucket": "dahl-4d255.firebasestorage.app"
  },
  "client": [
    {
      "client_info": {
        "mobilesdk_app_id": "1:504335149376:android:2f805704f2346b72eaf2a5",
        "android_client_info": {
          "package_name": "ru.dahl.messenger"
        }
      },
      "oauth_client": [],
      "api_key": [
        {
          "current_key": "AIzaSyCzzsWOebOWRgsmqkPD_lFRcG_T0kwie7Y"
        }
      ],
      "services": {
        "appinvite_service": {
          "other_platform_oauth_client": []
        }
      }
    },
    {
      "client_info": {
        "mobilesdk_app_id": "1:504335149376:android:33a337dabfd77319eaf2a5",
        "android_client_info": {
          "package_name": "ru.dahl.messenger.beta"
        }
      },
      "oauth_client": [],
      "api_key": [
        {
          "current_key": "AIzaSyCzzsWOebOWRgsmqkPD_lFRcG_T0kwie7Y"
        }
      ],
      "services": {
        "appinvite_service": {
          "other_platform_oauth_client": []
        }
      }
    }
  ],
  "configuration_version": "1"
}